[
  {
    "gamePkId": "530967",
    "road": "Rays,1,0,0,0,0,1,1,0,2,5,9,2",
    "home": "Orioles,1,0,0,2,1,0,8,3,X,15,15,1",
    "date": "2018-07-27"
  },
  {
    "gamePkId": "530963",
    "road": "Mets,3,0,0,0,0,1,0,0,0,4,9,0",
    "home": "Pirates,0,2,0,0,2,0,0,0,1,5,10,2",
    "date": "2018-07-27"
  },
  {
    "gamePkId": "530958",
    "road": "Indians,0,0,0,0,2,1,0,4,1,8,9,1",
    "home": "Tigers,0,0,2,0,0,1,0,0,0,3,10,0",
    "date": "2018-07-27"
  },
  {
    "gamePkId": "530962",
    "road": "Twins,0,0,0,0,0,0,1,0,2,0,3,6,0",
    "home": "Red Sox,0,0,0,0,2,0,0,0,1,1,4,8,1",
    "date": "2018-07-27"
  },
  {
    "gamePkId": "530965",
    "road": "Phillies,0,0,2,0,1,0,0,0,1,4,7,0",
    "home": "Reds,0,1,1,3,0,0,0,1,X,6,7,1",
    "date": "2018-07-27"
  },
  {
    "gamePkId": "530970",
    "road": "Nationals,1,1,2,0,0,0,0,5,0,9,16,3",
    "home": "Marlins,0,0,0,0,0,0,1,0,0,1,3,1",
    "date": "2018-07-27"
  },
  {
    "gamePkId": "530960",
    "road": "Dodgers,0,0,1,3,0,0,0,0,0,4,7,0",
    "home": "Braves,0,1,0,0,0,0,0,0,0,1,6,0",
    "date": "2018-07-27"
  },
  {
    "gamePkId": "530968",
    "road": "Rangers,0,1,0,0,2,2,0,1,5,11,15,0",
    "home": "Astros,0,0,0,0,0,0,1,0,1,2,6,1",
    "date": "2018-07-27"
  },
  {
    "gamePkId": "530969",
    "road": "Blue Jays,2,3,0,1,4,0,0,0,0,10,9,0",
    "home": "White Sox,0,0,1,0,0,0,1,0,3,5,11,1",
    "date": "2018-07-27"
  },
  {
    "gamePkId": "530957",
    "road": "Cubs,0,0,1,0,0,1,0,0,0,2,8,1",
    "home": "Cardinals,0,0,2,3,0,0,0,0,X,5,12,0",
    "date": "2018-07-27"
  },
  {
    "gamePkId": "530964",
    "road": "Athletics,0,0,0,0,0,0,1,0,0,1,9,0",
    "home": "Rockies,0,1,0,0,2,0,0,0,X,3,10,1",
    "date": "2018-07-27"
  },
  {
    "gamePkId": "530966",
    "road": "Mariners,0,0,0,0,1,0,1,1,0,0,3,9,0",
    "home": "Angels,0,3,0,0,0,0,0,0,0,1,4,7,1",
    "date": "2018-07-27"
  },
  {
    "gamePkId": "530956",
    "road": "D-backs,0,0,6,0,0,0,0,0,0,6,11,0",
    "home": "Padres,0,1,0,0,0,0,0,1,0,2,8,1",
    "date": "2018-07-27"
  },
  {
    "gamePkId": "530961",
    "road": "Brewers,0,0,0,0,0,1,1,1,0,3,6,0",
    "home": "Giants,0,1,0,0,0,0,0,0,0,1,6,1",
    "date": "2018-07-27"
  }
]