[
  {
    "gamePkId": "531687",
    "road": "Cardinals,0,0,0,0,1,1,0,1,0,3,8,1",
    "home": "Braves,0,0,0,2,3,0,1,1,X,7,7,0",
    "date": "2018-09-19"
  },
  {
    "gamePkId": "531683",
    "road": "Twins,0,4,0,2,0,0,0,2,0,8,11,0",
    "home": "Tigers,0,0,0,0,0,0,0,0,2,2,4,1",
    "date": "2018-09-19"
  },
  {
    "gamePkId": "531688",
    "road": "Rays,0,3,1,4,0,0,0,1,0,9,16,0",
    "home": "Rangers,0,0,1,1,0,1,0,0,0,3,7,2",
    "date": "2018-09-19"
  },
  {
    "gamePkId": "531684",
    "road": "Mets,0,0,0,0,0,0,0,0,0,0,6,1",
    "home": "Phillies,1,0,0,2,1,0,0,0,X,4,7,2",
    "date": "2018-09-19"
  },
  {
    "gamePkId": "531676",
    "road": "Red Sox,0,0,0,0,1,0,0,0,0,1,9,1",
    "home": "Yankees,0,3,0,1,0,4,0,2,X,10,11,0",
    "date": "2018-09-19"
  },
  {
    "gamePkId": "531681",
    "road": "Royals,0,0,1,0,0,0,0,0,0,1,6,0",
    "home": "Pirates,0,1,0,0,1,0,0,0,X,2,9,1",
    "date": "2018-09-19"
  },
  {
    "gamePkId": "531689",
    "road": "Blue Jays,0,0,0,0,0,0,0,1,0,1,4,1",
    "home": "Orioles,0,0,1,0,0,0,1,0,X,2,6,0",
    "date": "2018-09-19"
  },
  {
    "gamePkId": "531678",
    "road": "White Sox,0,0,0,0,0,1,0,0,0,1,5,0",
    "home": "Indians,0,0,0,0,0,0,0,0,4,4,5,2",
    "date": "2018-09-19"
  },
  {
    "gamePkId": "531679",
    "road": "Reds,0,0,0,0,0,0,0,0,0,0,2,0",
    "home": "Brewers,1,0,3,0,0,3,0,0,X,7,7,0",
    "date": "2018-09-19"
  },
  {
    "gamePkId": "531686",
    "road": "Mariners,3,0,0,0,2,1,2,1,0,9,11,0",
    "home": "Astros,0,0,0,0,0,0,0,0,0,0,5,0",
    "date": "2018-09-19"
  },
  {
    "gamePkId": "531685",
    "road": "Giants,0,3,0,0,0,0,0,1,0,4,8,0",
    "home": "Padres,0,5,0,0,0,0,0,3,X,8,10,1",
    "date": "2018-09-19"
  },
  {
    "gamePkId": "531677",
    "road": "Cubs,0,0,0,0,0,0,0,0,0,0,1,1",
    "home": "D-backs,4,0,0,0,0,3,0,2,X,9,12,1",
    "date": "2018-09-19"
  },
  {
    "gamePkId": "531682",
    "road": "Angels,0,0,0,0,0,0,0,0,0,0,4,1",
    "home": "Athletics,0,0,0,6,3,0,1,0,X,10,10,0",
    "date": "2018-09-19"
  },
  {
    "gamePkId": "531680",
    "road": "Rockies,2,0,0,0,0,0,0,0,0,2,4,0",
    "home": "Dodgers,0,1,0,0,1,0,3,0,X,5,5,2",
    "date": "2018-09-19"
  }
]